{"cameraMode":{"drawMode":0,"name":"Shaded","section":"Shading Mode"},"sceneLighting":false,"audioPlay":false,"sceneViewState":{"showFog":true,"showMaterialUpdate":false,"showSkybox":false,"showFlares":true,"showImageEffects":true,"showParticleSystems":true,"showVisualEffectGraphs":true,"m_FxEnabled":true},"in2DMode":false,"pivot":{"x":0.0022069215774536134,"y":-0.006884634494781494,"z":2.243804454803467},"rotation":{"x":0.7071068286895752,"y":0.0,"z":0.0,"w":0.7071068286895752},"size":3.28841495513916,"orthographic":false}